tgenv/__init__.py
tgenv/asset_downloader.py
tgenv/console_logger_format.py
tgenv/file_handler.py
tgenv/git_wrapper.py
tgenv/main.py
tgenv/version_handler.py
tgenv/res/default.conf
tgenv/res/quotes
tgenv-1.3.3.data/data/config/default.conf
tgenv-1.3.3.data/data/config/quotes
tgenv-1.3.3.dist-info/LICENSE
tgenv-1.3.3.dist-info/METADATA
tgenv-1.3.3.dist-info/WHEEL
tgenv-1.3.3.dist-info/entry_points.txt
tgenv-1.3.3.dist-info/top_level.txt
tgenv-1.3.3.dist-info/RECORD
