Metadata-Version: 2.1
Name: tgenv
Version: 1.3.3
Summary: A tool for managing terragrunt versions
Home-page: https://gitlab.com/claudiuskastner/tgenv
Author: Claudius Kastner
Author-email: claukast@gmail.com
License: GPL-3.0-only
Keywords: terragrunt terraform versioning
Classifier: Environment :: Console
Classifier: Intended Audience :: Developers
Classifier: Intended Audience :: System Administrators
Classifier: Operating System :: POSIX
Classifier: Programming Language :: Python
Requires-Python: >=3.6
License-File: LICENSE
Requires-Dist: click
Requires-Dist: requests
Requires-Dist: tqdm
Requires-Dist: PyGithub
